tops/dynamic.py
tops/modal_analysis.py
tops/plotting.py
tops/solvers.py
tops/utility_functions.py
tops/dyn_models/__init__.py
tops/dyn_models/avr.py
tops/dyn_models/blocks.py
tops/dyn_models/gen.py
tops/dyn_models/gov.py
tops/dyn_models/lines.py
tops/dyn_models/loads.py
tops/dyn_models/pll.py
tops/dyn_models/pss.py
tops/dyn_models/shunts.py
tops/dyn_models/trafos.py
tops/dyn_models/utils.py
tops/dyn_models/vsc.py
tops/ps_models/__init__.py
tops/ps_models/ieee39.py
tops/ps_models/ieee39_all_ctrl.py
tops/ps_models/ieee68.py
tops/ps_models/k2a.py
tops/ps_models/k2a_val.py
tops/ps_models/n44.py
tops/ps_models/sm_ib.py
tops/ps_models/sm_ib_kundur.py
tops/ps_models/sm_load.py
tops-0.2.0.dist-info/LICENSE
tops-0.2.0.dist-info/METADATA
tops-0.2.0.dist-info/WHEEL
tops-0.2.0.dist-info/top_level.txt
tops-0.2.0.dist-info/RECORD
