Metadata-Version: 2.1
Name: tops
Version: 0.2.0
Summary: Tiny open power system simulator
Author-email: Hallvar Haugdal <hallvar.haugdal@sintef.no>
License: MIT License
Project-URL: Homepage, https://github.com/hallvar-h/TOPS
Project-URL: Bug Tracker, https://github.com/hallvar-h/TOPS/issues
Classifier: Programming Language :: Python :: 3
Classifier: Operating System :: OS Independent
Requires-Python: >=3.7
License-File: LICENSE
Requires-Dist: numpy
Requires-Dist: scipy
Requires-Dist: matplotlib
Requires-Dist: pandas
